ipl/__init__.py
ipl/__main__.py
ipl/_logging.py
ipl/entry.py
ipl/errors.py
ipl/image_analysis.py
ipl/image_processor.py
ipl/importexport.py
ipl/logging_.py
ipl/visualization.py
ipl/workflows.py
ipl/database/__init__.py
ipl/database/image_db.py
ipl/database/__pycache__/__init__.cpython-36.pyc
ipl/database/__pycache__/image_db.cpython-36.pyc
ipl/database/datasource/images.db
ipl/database/scripts/check_if_field_exists.sql
ipl/database/scripts/check_if_has_cached_statistics.sql
ipl/database/scripts/check_if_image_details_exist.sql
ipl/database/scripts/check_if_image_exists.sql
ipl/database/scripts/insert_field.sql
ipl/database/scripts/insert_image.sql
ipl/database/scripts/insert_image_statistics.sql
ipl/database/scripts/select_field_statistics.sql
ipl/database/scripts/select_images.sql
cmdline_image_processor-0.2.3.dist-info/LICENCE.txt
cmdline_image_processor-0.2.3.dist-info/METADATA
cmdline_image_processor-0.2.3.dist-info/WHEEL
cmdline_image_processor-0.2.3.dist-info/entry_points.txt
cmdline_image_processor-0.2.3.dist-info/top_level.txt
cmdline_image_processor-0.2.3.dist-info/RECORD
